__init__.py
__main__.py
cli.py
main.py
cli/__init__.py
cli/base_command.py
cli/base_commands.py
cli/host_commands.py
cli/vm_commands.py
cli_bak/__init__.py
cli_bak/base_commands.py
cli_bak/host_commands.py
cli_bak/vm_commands.py
core/__init__.py
core/authenticator.py
core/command_metadata.py
core/config_manager.py
core/connection.py
core_bak/__init__.py
core_bak/authenticator.py
core_bak/command_metadata.py
core_bak/config_manager.py
core_bak/connection.py
esxi_testing_toolkit/__init__.py
esxi_testing_toolkit/__main__.py
esxi_testing_toolkit/main.py
esxi_testing_toolkit/cli/__init__.py
esxi_testing_toolkit/cli/base_commands.py
esxi_testing_toolkit/cli/host_commands.py
esxi_testing_toolkit/cli/vm_commands.py
esxi_testing_toolkit/core/__init__.py
esxi_testing_toolkit/core/authenticator.py
esxi_testing_toolkit/core/command_metadata.py
esxi_testing_toolkit/core/config_manager.py
esxi_testing_toolkit/core/connection.py
esxi_testing_toolkit-0.1.8.dist-info/LICENSE
esxi_testing_toolkit-0.1.8.dist-info/METADATA
esxi_testing_toolkit-0.1.8.dist-info/WHEEL
esxi_testing_toolkit-0.1.8.dist-info/entry_points.txt
esxi_testing_toolkit-0.1.8.dist-info/top_level.txt
esxi_testing_toolkit-0.1.8.dist-info/RECORD
