Metadata-Version: 2.2
Name: esxi-testing-toolkit
Version: 0.1.8
Summary: Simple and easy to use CLI tool to test ESXi detections.
Author-email: Nathan Burns <contact@nburns.tech>
Maintainer-email: Nathan Burns <contact@nburns.tech>
License: MIT License
Project-URL: Repository, https://github.com/AlbinoGazelle/esxi-testing-toolkit.git
Keywords: security,esxi,infosec,security-tools,threat-detection,detection-engineering
License-File: LICENSE
Requires-Dist: typer~=0.15.1
Requires-Dist: xmltodict~=0.14.2
Requires-Dist: requests~=2.32.3
Requires-Dist: python-dotenv
Requires-Dist: paramiko~=3.5.0
Requires-Dist: tabulate~=0.9.0
